lotto/__init__.py
lotto/cli.py
lotto/controllers.py
lotto/main.py
lotto/models.py
lotto/views.py
thath_lotto-0.1.1.dist-info/entry_points.txt
thath_lotto-0.1.1.dist-info/WHEEL
thath_lotto-0.1.1.dist-info/METADATA
thath_lotto-0.1.1.dist-info/RECORD
