Metadata-Version: 2.1
Name: thath-lotto
Version: 0.1.1
Summary: This is a small lottery game
License: BSD
Author: Travis Hathaway
Author-email: travis.j.hathaway@gmail.com
Requires-Python: >=3.8,<4.0
Classifier: License :: Other/Proprietary License
Classifier: Programming Language :: Python :: 3
Classifier: Programming Language :: Python :: 3.10
Classifier: Programming Language :: Python :: 3.8
Classifier: Programming Language :: Python :: 3.9
